surface_fitter/__init__.py
surface_fitter/fit_poly_3d.py
surface_fitter/main.py
surface_fitter/plot_scatter_3d.py
surface_fitter/surface_generator.py
surface_fitter-0.16.dist-info/licenses/LICENSE
surface_fitter-0.16.dist-info/METADATA
surface_fitter-0.16.dist-info/WHEEL
surface_fitter-0.16.dist-info/top_level.txt
surface_fitter-0.16.dist-info/RECORD
