Metadata-Version: 2.4
Name: surface_fitter
Version: 0.16
Summary: Least-square fitting of 3D surface to data points in text file
License-File: LICENSE
Dynamic: license-file
